informal_detector/__init__.py
informal_detector/is_informal.py
informal_detector-0.1.2.dist-info/LICENSE
informal_detector-0.1.2.dist-info/METADATA
informal_detector-0.1.2.dist-info/WHEEL
informal_detector-0.1.2.dist-info/top_level.txt
informal_detector-0.1.2.dist-info/RECORD
