Metadata-Version: 2.1
Name: informal-detector
Version: 0.1.2
Summary: A Python package to check if a text is informal Persian.
Home-page: https://github.com/MahtaFetrat/Persian-Informal-Text-Detector
Author: Mahta Fetrat
Author-email: 77fetrat@gmail.com
License: UNKNOWN
Platform: UNKNOWN
Classifier: Programming Language :: Python :: 3
Classifier: Programming Language :: Python :: 2.7
Classifier: License :: OSI Approved :: GNU General Public License (GPL)
Classifier: Operating System :: OS Independent
Requires-Python: >=2.7
License-File: LICENSE
